{"resource_id":"feat","stats":{"name":{"value":"Tough"},"source":{"value":"phb"},"descriptions":{"value":[{"resource_id":"levelled_description","stats":{"description":{"value":"Your hit point maximum increases by an amount equal to twice your level when you gain this feat. Whenever you gain a level thereafter, your hit point maximum increases by an additional 2 hit points"},"updated_at":{"value":"2024-12-20T18:50:28.390245"},"id":"96b8c1c7-4698-4f04-b3b7-7c703218eeff"}}]},"effects":{"value":[{"resource_id":"levelled_effect","stats":{"effect":{"value":{"resource_id":"effect","stats":{"name":{"value":"Tough"},"trigger_condition":{"value":{"resource_id":"trigger_condition_or","stats":{"id":"306014a9-bd2e-454d-974e-99a206ae669d"}}},"id":"cdbb6071-c6a4-4ff9-8038-0b6779d3858a"}}},"id":"eae9e637-4e72-4d03-a53c-fd93b037166c"}}]},"updated_at":{"value":"2024-12-20T18:50:28.390252"},"id":"tough"}}