{"resource_id":"spell","stats":{"id":"vortex_warp","name":{"value":"Vortex Warp"},"source":{"value":"scc"},"level":{"value":"spell_level_2"},"school":{"value":"spell_school_conjuration"},"ritual":{"value":false},"casting_time":{"value":"1 action"},"range":{"value":"90 feet"},"duration":{"value":"Instantaneous"},"verbal":{"value":true},"somatic":{"value":true},"material":{"value":false},"description":{"value":"You magically twist space around another creature you can see within range. The target must succeed on a Constitution saving throw (the target can choose to fail), or the target is teleported to an unoccupied space of your choice that you can see within range. The chosen space must be on a surface or in a liquid that can support the target without the target having to squeeze."},"higher_level_description":{"value":"When you cast this spell using a spell slot of 3rd level or higher, the range of the spell increases by 30 feet for each slot level above 2nd."},"classes":{"value":["artificer","artificer__revised_","artificer__eb_","wizard","sorcerer"]},"dice":{"value":[]},"updated_at":{"value":"2024-12-20T18:50:46.704167"}}}