{"resource_id":"spell","stats":{"name":{"value":"Cordon Of Arrows"},"source":{"value":"phb"},"level":{"value":"spell_level_2"},"school":{"value":"spell_school_transmutation"},"casting_time":{"value":"1 action"},"range":{"value":"5 feet"},"duration":{"value":"8 hours"},"verbal":{"value":true},"somatic":{"value":true},"material":{"value":true},"components":{"value":"four or more arrows or bolts"},"description":{"value":"You plant four pieces of nonmagical ammunition—arrows or crossbow bolts—in the ground within range and lay magic upon them to protect an area. Until the spell ends, whenever a creature other than you comes within 30 feet of the ammunition for the first time on a turn or ends its turn there, one piece of ammunition flies up to strike it. The creature must succeed on a Dexterity saving throw or take 1d6 piercing damage. The piece of ammunition is then destroyed. The spell ends when no ammunition remains.\n\nWhen you cast this spell, you can designate any creatures you choose, and the spell ignores them."},"higher_level_description":{"value":"When you cast this spell using a spell slot of 3rd level or higher, the amount of ammunition that can be affected increases by two for each slot level above 2nd."},"classes":{"value":["revised_ranger","ranger"]},"dice":{"value":[{"resource_id":"levelled_damage_dice","stats":{"level":{"value":2},"damage_dice":{"value":[{"resource_id":"damage_dice","stats":{"dices":{"value":[{"resource_id":"dice_roll","stats":{"dice_amount":{"value":1},"dice_type":{"value":"d6"},"updated_at":{"value":"2024-12-20T18:50:46.637623"},"id":"b4063a40-6794-4994-8548-3e8bbe7f8c15"}}]},"damage_type":{"value":"piercing"},"updated_at":{"value":"2024-12-20T18:50:46.637629"},"id":"9ed4c41e-55ee-475c-beb1-afe7cb6dffe6"}}]},"updated_at":{"value":"2024-12-20T18:50:46.637634"},"id":"23f175d0-63dd-4808-8e8f-79b92dbfa9c5"}}]},"updated_at":{"value":"2024-12-20T18:50:46.637640"},"id":"cordon_of_arrows"}}